{
  "radius": 100.0,
  "points": {
    "1": {
      "type": "NORMAL",
      "$type": "DungeonQuitPoint",
      "gadgetId": 70120004,
      "pos": {
        "x": 5.681675,
        "y": -0.0568980575,
        "z": 69.25831
      },
      "rot": {
        "x": 0.0,
        "y": 0.0,
        "z": 0.0
      },
      "areaId": 0,
      "unlocked": true,
      "cutsceneList": [],
      "groupLimit": false,
      "size": {
        "x": 5.0,
        "y": 5.0,
        "z": 5.0
      },
      "titleTextID": ""
    }
  },
  "areas": {},
  "forces": {},
  "entities": {
    "1": {
      "$type": "ConfigLocalTrigger",
      "gadgetId": 70010006,
      "pos": {
        "x": -0.485409141,
        "y": -21.54844,
        "z": -5.20052338
      },
      "rot": {
        "x": 0.0,
        "y": 0.0,
        "z": 0.0
      },
      "areaId": 0,
      "unlocked": true,
      "checkDist": 100.0,
      "withGO": false,
      "triggerFlag": "LevelAbility",
      "shape": {
        "$type": "ConfigShapeRect",
        "useHeight": true,
        "height": 10.0,
        "centerType": "Center",
        "width": 240.0,
        "length": 240.0
      },
      "checkCount": 0,
      "vectorParam": {
        "x": 0.0,
        "y": 0.0,
        "z": 0.0
      },
      "floatParam": 0.0,
      "stringParam": "Dvalin_S04_DeadRegion"
    }
  },
  "doors": {}
}