{
  "sceneId": 40008,
  "monsters": [
    {
      "groupId": 240008001,
      "mapInstId": 1001,
      "aiSensingTemplate": "DefaultTemplate",
      "aiNeuronSetting": "DefaultSetting"
    },
    {
      "groupId": 240008001,
      "mapInstId": 1002,
      "aiSensingTemplate": "DefaultTemplate",
      "aiNeuronSetting": "DefaultSetting"
    },
    {
      "groupId": 240008001,
      "mapInstId": 1003,
      "aiSensingTemplate": "DefaultTemplate",
      "aiNeuronSetting": "DefaultSetting"
    },
    {
      "groupId": 240008001,
      "mapInstId": 1004,
      "aiSensingTemplate": "DefaultTemplate",
      "aiNeuronSetting": "DefaultSetting"
    },
    {
      "groupId": 240008001,
      "mapInstId": 1005,
      "aiSensingTemplate": "DefaultTemplate",
      "aiNeuronSetting": "DefaultSetting"
    },
    {
      "groupId": 240008002,
      "mapInstId": 2005,
      "aiSensingTemplate": "DefaultTemplate",
      "aiNeuronSetting": "DefaultSetting"
    },
    {
      "groupId": 240008002,
      "mapInstId": 2006,
      "aiSensingTemplate": "DefaultTemplate",
      "aiNeuronSetting": "DefaultSetting"
    },
    {
      "groupId": 240008002,
      "mapInstId": 2007,
      "aiSensingTemplate": "DefaultTemplate",
      "aiNeuronSetting": "DefaultSetting"
    },
    {
      "groupId": 240008002,
      "mapInstId": 2008,
      "aiSensingTemplate": "DefaultTemplate",
      "aiNeuronSetting": "DefaultSetting"
    },
    {
      "groupId": 240008002,
      "mapInstId": 2009,
      "aiSensingTemplate": "DefaultTemplate",
      "aiNeuronSetting": "DefaultSetting"
    },
    {
      "groupId": 240008002,
      "mapInstId": 2010,
      "aiSensingTemplate": "DefaultTemplate",
      "aiNeuronSetting": "DefaultSetting"
    },
    {
      "groupId": 240008002,
      "mapInstId": 2011,
      "aiSensingTemplate": "DefaultTemplate",
      "aiNeuronSetting": "DefaultSetting"
    },
    {
      "groupId": 240008002,
      "mapInstId": 2012,
      "aiSensingTemplate": "DefaultTemplate",
      "aiNeuronSetting": "DefaultSetting"
    },
    {
      "groupId": 240008002,
      "mapInstId": 2013,
      "aiSensingTemplate": "DefaultTemplate",
      "aiNeuronSetting": "DefaultSetting"
    },
    {
      "groupId": 240008002,
      "mapInstId": 2014,
      "aiSensingTemplate": "DefaultTemplate",
      "aiNeuronSetting": "DefaultSetting"
    },
    {
      "groupId": 240008002,
      "mapInstId": 2015,
      "aiSensingTemplate": "DefaultTemplate",
      "aiNeuronSetting": "DefaultSetting"
    },
    {
      "groupId": 240008002,
      "mapInstId": 2016,
      "aiSensingTemplate": "DefaultTemplate",
      "aiNeuronSetting": "DefaultSetting"
    },
    {
      "groupId": 240008002,
      "mapInstId": 2027,
      "aiSensingTemplate": "DefaultTemplate",
      "aiNeuronSetting": "DefaultSetting"
    },
    {
      "groupId": 240008003,
      "mapInstId": 3002,
      "aiSensingTemplate": "DefaultTemplate",
      "aiNeuronSetting": "DefaultSetting"
    },
    {
      "groupId": 240008003,
      "mapInstId": 3003,
      "aiSensingTemplate": "DefaultTemplate",
      "aiNeuronSetting": "DefaultSetting"
    },
    {
      "groupId": 240008003,
      "mapInstId": 3004,
      "aiSensingTemplate": "DefaultTemplate",
      "aiNeuronSetting": "DefaultSetting"
    },
    {
      "groupId": 240008003,
      "mapInstId": 3005,
      "aiSensingTemplate": "DefaultTemplate",
      "aiNeuronSetting": "DefaultSetting"
    },
    {
      "groupId": 240008003,
      "mapInstId": 3006,
      "aiSensingTemplate": "DefaultTemplate",
      "aiNeuronSetting": "DefaultSetting"
    },
    {
      "groupId": 240008003,
      "mapInstId": 3007,
      "aiSensingTemplate": "DefaultTemplate",
      "aiNeuronSetting": "DefaultSetting"
    },
    {
      "groupId": 240008003,
      "mapInstId": 3008,
      "aiSensingTemplate": "DefaultTemplate",
      "aiNeuronSetting": "DefaultSetting"
    },
    {
      "groupId": 240008003,
      "mapInstId": 3009,
      "aiSensingTemplate": "DefaultTemplate",
      "aiNeuronSetting": "DefaultSetting"
    },
    {
      "groupId": 240008003,
      "mapInstId": 3010,
      "aiSensingTemplate": "DefaultTemplate",
      "aiNeuronSetting": "DefaultSetting"
    },
    {
      "groupId": 240008003,
      "mapInstId": 3011,
      "aiSensingTemplate": "DefaultTemplate",
      "aiNeuronSetting": "DefaultSetting"
    },
    {
      "groupId": 240008003,
      "mapInstId": 3012,
      "aiSensingTemplate": "DefaultTemplate",
      "aiNeuronSetting": "DefaultSetting"
    }
  ]
}